{
  "schemaVersion": 1,
  "id": "simple_server_roles",
  "version": "${version}",

  "name": "Simple Server Roles",
  "description": "A Fabric mod, which allows players to self-manage their roles (teams)",
  "authors": [
    "simonmicro"
  ],
  "contact": {
    "homepage": "https://simonmicro.de/",
    "sources": "https://gitlab.simonmicro.de/minecraft-modding/simple-server-roles"
  },

  "license": "AGPL-3",
  "icon": "assets/simple_server_roles/icon.png",

  "environment": "*",
  "entrypoints": {
    "main": [
      "com.simonmicro.simple_server_roles.SimpleServerRoles"
    ]
  },
  "mixins": [],

  "depends": {
    "fabricloader": ">=0.14.11",
    "fabric-api": "*",
    "minecraft": "~1.19.3",
    "java": ">=17"
  },
  "suggests": {}
}
